README.rst
setup.py
weidao/__init__.py
weidao/heytest.py
weidao.egg-info/PKG-INFO
weidao.egg-info/SOURCES.txt
weidao.egg-info/dependency_links.txt
weidao.egg-info/requires.txt
weidao.egg-info/top_level.txt