Metadata-Version: 1.1
Name: weidao
Version: 0.1.0
Summary: weidao
Home-page: https://github.com/tonglei100/weidao
Author: Leo Tong
Author-email: tonglei@qq.com
License: Apache License, Version 2.0
Platform: UNKNOWN
Classifier: Environment :: Web Environment
Classifier: Intended Audience :: Developers
Classifier: Operating System :: OS Independent
Classifier: Topic :: Software Development :: Libraries :: Python Modules
Classifier: Programming Language :: Python :: 3.6
